setup.py
halocode/__init__.py
halocode-0.0.4.dist-info/METADATA
halocode-0.0.4.dist-info/WHEEL
halocode-0.0.4.dist-info/top_level.txt
halocode-0.0.4.dist-info/RECORD
