Metadata-Version: 2.1
Name: halocode
Version: 0.0.4
Summary: library for makeblock halocode
Home-page: https://makeblock.com
Author: makeblock
Author-email: flashindream@gmail.com
License: UNKNOWN
Platform: UNKNOWN
Requires-Dist: makeblock
